Metadata-Version: 2.1
Name: cachegenius
Version: 0.1.0
Summary: Speed-up your code by automatically identifying functions that should use caching in your code!
Home-page: https://github.com/NicolasMICAUX/cachegenius
Author: Nicolas Micaux
Keywords: cache,caching,automatically
Classifier: Development Status :: 3 - Alpha
Classifier: Intended Audience :: Developers
Classifier: Natural Language :: English
Classifier: Topic :: Utilities
Classifier: Programming Language :: Python :: 3
Classifier: Programming Language :: Python :: 3.5
Classifier: Programming Language :: Python :: 3.6
Classifier: Programming Language :: Python :: 3.7
Classifier: Programming Language :: Python :: 3.8
Classifier: Programming Language :: Python :: 3.9
Classifier: Programming Language :: Python :: 3.10
Classifier: Programming Language :: Python :: 3.11
Requires-Python: >=3.5
